lazify.py
Lazify-0.3.1.dist-info/DESCRIPTION.rst
Lazify-0.3.1.dist-info/METADATA
Lazify-0.3.1.dist-info/RECORD
Lazify-0.3.1.dist-info/WHEEL
Lazify-0.3.1.dist-info/metadata.json
Lazify-0.3.1.dist-info/top_level.txt
