Metadata-Version: 2.0
Name: Lazify
Version: 0.3.1
Summary: Lazify all the things!
Home-page: https://github.com/numberly/lazify
Author: Guillaume Gelin
Author-email: ramnes@1000mercis.com
License: BSD
Platform: any
Classifier: Intended Audience :: Developers
Classifier: Operating System :: OS Independent
Classifier: Programming Language :: Python
Classifier: Topic :: Software Development :: Libraries :: Python Modules
